{
  "prices": [
    {
      "date": "2026-02-24",
      "open": 6083.0,
      "high": 6173.5,
      "low": 6065.5,
      "close": 6162.5,
      "volume": 193510,
      "dma_50": 6162.5,
      "dma_200": 6162.5
    },
    {
      "date": "2026-02-25",
      "open": 6170.0,
      "high": 6208.5,
      "low": 6140.0,
      "close": 6158.0,
      "volume": 253773,
      "dma_50": 6160.25,
      "dma_200": 6160.25
    },
    {
      "date": "2026-02-26",
      "open": 6158.0,
      "high": 6187.0,
      "low": 6070.0,
      "close": 6137.0,
      "volume": 245317,
      "dma_50": 6152.5,
      "dma_200": 6152.5
    },
    {
      "date": "2026-02-27",
      "open": 6135.5,
      "high": 6142.5,
      "low": 5975.0,
      "close": 6002.5,
      "volume": 350612,
      "dma_50": 6115.0,
      "dma_200": 6115.0
    },
    {
      "date": "2026-03-02",
      "open": 5866.0,
      "high": 6001.0,
      "low": 5866.0,
      "close": 5959.0,
      "volume": 185417,
      "dma_50": 6083.8,
      "dma_200": 6083.8
    },
    {
      "date": "2026-03-04",
      "open": 5901.5,
      "high": 5924.0,
      "low": 5845.5,
      "close": 5889.5,
      "volume": 293377,
      "dma_50": 6051.42,
      "dma_200": 6051.42
    },
    {
      "date": "2026-03-05",
      "open": 5899.0,
      "high": 5997.5,
      "low": 5851.0,
      "close": 5963.0,
      "volume": 211179,
      "dma_50": 6038.79,
      "dma_200": 6038.79
    },
    {
      "date": "2026-03-06",
      "open": 5948.0,
      "high": 6013.0,
      "low": 5926.5,
      "close": 5983.0,
      "volume": 348722,
      "dma_50": 6031.81,
      "dma_200": 6031.81
    },
    {
      "date": "2026-03-09",
      "open": 5930.0,
      "high": 5932.5,
      "low": 5815.5,
      "close": 5890.0,
      "volume": 245594,
      "dma_50": 6016.06,
      "dma_200": 6016.06
    },
    {
      "date": "2026-03-10",
      "open": 5911.0,
      "high": 5995.0,
      "low": 5911.0,
      "close": 5968.0,
      "volume": 283327,
      "dma_50": 6011.25,
      "dma_200": 6011.25
    },
    {
      "date": "2026-03-11",
      "open": 5981.0,
      "high": 5995.0,
      "low": 5900.0,
      "close": 5921.5,
      "volume": 298621,
      "dma_50": 6003.09,
      "dma_200": 6003.09
    },
    {
      "date": "2026-03-12",
      "open": 5910.0,
      "high": 5910.0,
      "low": 5713.0,
      "close": 5787.0,
      "volume": 996754,
      "dma_50": 5985.08,
      "dma_200": 5985.08
    },
    {
      "date": "2026-03-13",
      "open": 5750.0,
      "high": 5881.0,
      "low": 5727.0,
      "close": 5808.5,
      "volume": 738522,
      "dma_50": 5971.5,
      "dma_200": 5971.5
    },
    {
      "date": "2026-03-16",
      "open": 5808.5,
      "high": 5872.5,
      "low": 5764.5,
      "close": 5842.0,
      "volume": 350827,
      "dma_50": 5962.25,
      "dma_200": 5962.25
    },
    {
      "date": "2026-03-17",
      "open": 5849.0,
      "high": 5868.5,
      "low": 5801.5,
      "close": 5857.5,
      "volume": 260165,
      "dma_50": 5955.27,
      "dma_200": 5955.27
    },
    {
      "date": "2026-03-18",
      "open": 5860.5,
      "high": 5914.0,
      "low": 5842.0,
      "close": 5885.0,
      "volume": 301564,
      "dma_50": 5950.88,
      "dma_200": 5950.88
    },
    {
      "date": "2026-03-19",
      "open": 5799.0,
      "high": 5852.0,
      "low": 5642.5,
      "close": 5673.5,
      "volume": 234382,
      "dma_50": 5934.56,
      "dma_200": 5934.56
    },
    {
      "date": "2026-03-20",
      "open": 5735.0,
      "high": 5749.5,
      "low": 5592.0,
      "close": 5618.5,
      "volume": 462806,
      "dma_50": 5917.0,
      "dma_200": 5917.0
    },
    {
      "date": "2026-03-23",
      "open": 5590.0,
      "high": 5590.5,
      "low": 5475.5,
      "close": 5490.0,
      "volume": 316325,
      "dma_50": 5894.53,
      "dma_200": 5894.53
    },
    {
      "date": "2026-03-24",
      "open": 5590.0,
      "high": 5600.0,
      "low": 5404.5,
      "close": 5513.5,
      "volume": 542902,
      "dma_50": 5875.48,
      "dma_200": 5875.48
    }
  ]
}